cbi_auth/__init__.py
cbi_auth/helpers/__init__.py
cbi_auth/interfaces/__init__.py
cbi_auth/repositories/__init__.py
cbi_auth/repositories/auth_repository.py
tests/__init__.py
cbi_auth-1.0.0.dist-info/LICENSE
cbi_auth-1.0.0.dist-info/METADATA
cbi_auth-1.0.0.dist-info/WHEEL
cbi_auth-1.0.0.dist-info/top_level.txt
cbi_auth-1.0.0.dist-info/zip-safe
cbi_auth-1.0.0.dist-info/RECORD
